geopypi/__init__.py
geopypi/common.py
geopypi/geopypi.py
Geopypi-0.0.5.dist-info/LICENSE
Geopypi-0.0.5.dist-info/METADATA
Geopypi-0.0.5.dist-info/WHEEL
Geopypi-0.0.5.dist-info/entry_points.txt
Geopypi-0.0.5.dist-info/top_level.txt
Geopypi-0.0.5.dist-info/RECORD
