Metadata-Version: 2.1
Name: Geopypi
Version: 0.0.5
Summary: This is a python package for batch geoprocessing.
Author-email: KH Shakibul Islam <kshakibu@vols.utk.edu>
License: MIT License
Project-URL: Homepage, https://github.com/Metaliguns77/Geopypi
Keywords: Geopypi
Classifier: Intended Audience :: Developers
Classifier: License :: OSI Approved :: MIT License
Classifier: Natural Language :: English
Classifier: Programming Language :: Python :: 3.8
Classifier: Programming Language :: Python :: 3.9
Classifier: Programming Language :: Python :: 3.10
Classifier: Programming Language :: Python :: 3.11
Classifier: Programming Language :: Python :: 3.12
Requires-Python: >=3.8
License-File: LICENSE
Requires-Dist: numpy
Requires-Dist: ipyleaflet
Provides-Extra: all
Requires-Dist: Geopypi[extra] ; extra == 'all'
Provides-Extra: extra
Requires-Dist: pandas ; extra == 'extra'
